{
  "metadata":{
    "source":"Qatar Calendar House (Dar Al-Taqweem Al-Qatri)",
    "url":"http://www.qatarch.com/",
    "timezone":"Asia/Qatar",
    "utc_offset":"+03:00",
    "total_days":365,
    "prayers":[
      {"id":"fajr","name_ar":"الفجر"},
      {"id":"sunrise","name_ar":"الشروق"},
      {"id":"dhuhr","name_ar":"الظهر"},
      {"id":"asr","name_ar":"العصر"},
      {"id":"maghrib","name_ar":"المغرب"},
      {"id":"isha","name_ar":"العشاء"}
    ]
  },
  "days":[
    {
      "date":"1/1",
      "day":1,
      "month":1,
      "prayers":{
        "fajr":"4:57",
        "sunrise":"6:20",
        "dhuhr":"11:37",
        "asr":"14:36",
        "maghrib":"16:57",
        "isha":"18:27"
      }
    },
    {
      "date":"2/1",
      "day":2,
      "month":1,
      "prayers":{
        "fajr":"4:57",
        "sunrise":"6:20",
        "dhuhr":"11:38",
        "asr":"14:36",
        "maghrib":"16:58",
        "isha":"18:28"
      }
    },
    {
      "date":"3/1",
      "day":3,
      "month":1,
      "prayers":{
        "fajr":"4:58",
        "sunrise":"6:20",
        "dhuhr":"11:38",
        "asr":"14:37",
        "maghrib":"16:59",
        "isha":"18:29"
      }
    },
    {
      "date":"4/1",
      "day":4,
      "month":1,
      "prayers":{
        "fajr":"4:58",
        "sunrise":"6:20",
        "dhuhr":"11:39",
        "asr":"14:38",
        "maghrib":"16:59",
        "isha":"18:29"
      }
    },
    {
      "date":"5/1",
      "day":5,
      "month":1,
      "prayers":{
        "fajr":"4:58",
        "sunrise":"6:20",
        "dhuhr":"11:39",
        "asr":"14:38",
        "maghrib":"17:00",
        "isha":"18:30"
      }
    },
    {
      "date":"6/1",
      "day":6,
      "month":1,
      "prayers":{
        "fajr":"4:58",
        "sunrise":"6:21",
        "dhuhr":"11:40",
        "asr":"14:39",
        "maghrib":"17:01",
        "isha":"18:31"
      }
    },
    {
      "date":"7/1",
      "day":7,
      "month":1,
      "prayers":{
        "fajr":"4:59",
        "sunrise":"6:21",
        "dhuhr":"11:40",
        "asr":"14:40",
        "maghrib":"17:01",
        "isha":"18:31"
      }
    },
    {
      "date":"8/1",
      "day":8,
      "month":1,
      "prayers":{
        "fajr":"4:59",
        "sunrise":"6:21",
        "dhuhr":"11:41",
        "asr":"14:40",
        "maghrib":"17:02",
        "isha":"18:32"
      }
    },
    {
      "date":"9/1",
      "day":9,
      "month":1,
      "prayers":{
        "fajr":"4:59",
        "sunrise":"6:21",
        "dhuhr":"11:41",
        "asr":"14:41",
        "maghrib":"17:03",
        "isha":"18:33"
      }
    },
    {
      "date":"10/1",
      "day":10,
      "month":1,
      "prayers":{
        "fajr":"4:59",
        "sunrise":"6:21",
        "dhuhr":"11:41",
        "asr":"14:42",
        "maghrib":"17:04",
        "isha":"18:34"
      }
    },
    {
      "date":"11/1",
      "day":11,
      "month":1,
      "prayers":{
        "fajr":"4:59",
        "sunrise":"6:21",
        "dhuhr":"11:42",
        "asr":"14:42",
        "maghrib":"17:04",
        "isha":"18:34"
      }
    },
    {
      "date":"12/1",
      "day":12,
      "month":1,
      "prayers":{
        "fajr":"5:00",
        "sunrise":"6:21",
        "dhuhr":"11:42",
        "asr":"14:43",
        "maghrib":"17:05",
        "isha":"18:35"
      }
    },
    {
      "date":"13/1",
      "day":13,
      "month":1,
      "prayers":{
        "fajr":"5:00",
        "sunrise":"6:21",
        "dhuhr":"11:43",
        "asr":"14:44",
        "maghrib":"17:06",
        "isha":"18:36"
      }
    },
    {
      "date":"14/1",
      "day":14,
      "month":1,
      "prayers":{
        "fajr":"5:00",
        "sunrise":"6:21",
        "dhuhr":"11:43",
        "asr":"14:44",
        "maghrib":"17:07",
        "isha":"18:37"
      }
    },
    {
      "date":"15/1",
      "day":15,
      "month":1,
      "prayers":{
        "fajr":"5:00",
        "sunrise":"6:21",
        "dhuhr":"11:43",
        "asr":"14:45",
        "maghrib":"17:07",
        "isha":"18:37"
      }
    },
    {
      "date":"16/1",
      "day":16,
      "month":1,
      "prayers":{
        "fajr":"5:00",
        "sunrise":"6:21",
        "dhuhr":"11:44",
        "asr":"14:46",
        "maghrib":"17:08",
        "isha":"18:38"
      }
    },
    {
      "date":"17/1",
      "day":17,
      "month":1,
      "prayers":{
        "fajr":"5:00",
        "sunrise":"6:21",
        "dhuhr":"11:44",
        "asr":"14:46",
        "maghrib":"17:09",
        "isha":"18:39"
      }
    },
    {
      "date":"18/1",
      "day":18,
      "month":1,
      "prayers":{
        "fajr":"5:00",
        "sunrise":"6:21",
        "dhuhr":"11:44",
        "asr":"14:47",
        "maghrib":"17:10",
        "isha":"18:40"
      }
    },
    {
      "date":"19/1",
      "day":19,
      "month":1,
      "prayers":{
        "fajr":"5:00",
        "sunrise":"6:21",
        "dhuhr":"11:45",
        "asr":"14:48",
        "maghrib":"17:10",
        "isha":"18:40"
      }
    },
    {
      "date":"20/1",
      "day":20,
      "month":1,
      "prayers":{
        "fajr":"5:00",
        "sunrise":"6:21",
        "dhuhr":"11:45",
        "asr":"14:48",
        "maghrib":"17:11",
        "isha":"18:41"
      }
    },
    {
      "date":"21/1",
      "day":21,
      "month":1,
      "prayers":{
        "fajr":"5:00",
        "sunrise":"6:21",
        "dhuhr":"11:45",
        "asr":"14:49",
        "maghrib":"17:12",
        "isha":"18:42"
      }
    },
    {
      "date":"22/1",
      "day":22,
      "month":1,
      "prayers":{
        "fajr":"5:00",
        "sunrise":"6:20",
        "dhuhr":"11:45",
        "asr":"14:50",
        "maghrib":"17:13",
        "isha":"18:43"
      }
    },
    {
      "date":"23/1",
      "day":23,
      "month":1,
      "prayers":{
        "fajr":"5:00",
        "sunrise":"6:20",
        "dhuhr":"11:46",
        "asr":"14:50",
        "maghrib":"17:13",
        "isha":"18:43"
      }
    },
    {
      "date":"24/1",
      "day":24,
      "month":1,
      "prayers":{
        "fajr":"4:59",
        "sunrise":"6:20",
        "dhuhr":"11:46",
        "asr":"14:51",
        "maghrib":"17:14",
        "isha":"18:44"
      }
    },
    {
      "date":"25/1",
      "day":25,
      "month":1,
      "prayers":{
        "fajr":"4:59",
        "sunrise":"6:20",
        "dhuhr":"11:46",
        "asr":"14:52",
        "maghrib":"17:15",
        "isha":"18:45"
      }
    },
    {
      "date":"26/1",
      "day":26,
      "month":1,
      "prayers":{
        "fajr":"4:59",
        "sunrise":"6:19",
        "dhuhr":"11:46",
        "asr":"14:52",
        "maghrib":"17:16",
        "isha":"18:46"
      }
    },
    {
      "date":"27/1",
      "day":27,
      "month":1,
      "prayers":{
        "fajr":"4:59",
        "sunrise":"6:19",
        "dhuhr":"11:47",
        "asr":"14:53",
        "maghrib":"17:16",
        "isha":"18:46"
      }
    },
    {
      "date":"28/1",
      "day":28,
      "month":1,
      "prayers":{
        "fajr":"4:59",
        "sunrise":"6:19",
        "dhuhr":"11:47",
        "asr":"14:53",
        "maghrib":"17:17",
        "isha":"18:47"
      }
    },
    {
      "date":"29/1",
      "day":29,
      "month":1,
      "prayers":{
        "fajr":"4:58",
        "sunrise":"6:18",
        "dhuhr":"11:47",
        "asr":"14:54",
        "maghrib":"17:18",
        "isha":"18:48"
      }
    },
    {
      "date":"30/1",
      "day":30,
      "month":1,
      "prayers":{
        "fajr":"4:58",
        "sunrise":"6:18",
        "dhuhr":"11:47",
        "asr":"14:55",
        "maghrib":"17:19",
        "isha":"18:49"
      }
    },
    {
      "date":"31/1",
      "day":31,
      "month":1,
      "prayers":{
        "fajr":"4:58",
        "sunrise":"6:18",
        "dhuhr":"11:47",
        "asr":"14:55",
        "maghrib":"17:19",
        "isha":"18:49"
      }
    },
    {
      "date":"1/2",
      "day":1,
      "month":2,
      "prayers":{
        "fajr":"4:58",
        "sunrise":"6:17",
        "dhuhr":"11:47",
        "asr":"14:56",
        "maghrib":"17:20",
        "isha":"18:50"
      }
    },
    {
      "date":"2/2",
      "day":2,
      "month":2,
      "prayers":{
        "fajr":"4:57",
        "sunrise":"6:17",
        "dhuhr":"11:48",
        "asr":"14:56",
        "maghrib":"17:21",
        "isha":"18:51"
      }
    },
    {
      "date":"3/2",
      "day":3,
      "month":2,
      "prayers":{
        "fajr":"4:57",
        "sunrise":"6:16",
        "dhuhr":"11:48",
        "asr":"14:57",
        "maghrib":"17:22",
        "isha":"18:52"
      }
    },
    {
      "date":"4/2",
      "day":4,
      "month":2,
      "prayers":{
        "fajr":"4:56",
        "sunrise":"6:16",
        "dhuhr":"11:48",
        "asr":"14:57",
        "maghrib":"17:22",
        "isha":"18:52"
      }
    },
    {
      "date":"5/2",
      "day":5,
      "month":2,
      "prayers":{
        "fajr":"4:56",
        "sunrise":"6:15",
        "dhuhr":"11:48",
        "asr":"14:58",
        "maghrib":"17:23",
        "isha":"18:53"
      }
    },
    {
      "date":"6/2",
      "day":6,
      "month":2,
      "prayers":{
        "fajr":"4:56",
        "sunrise":"6:15",
        "dhuhr":"11:48",
        "asr":"14:58",
        "maghrib":"17:24",
        "isha":"18:54"
      }
    },
    {
      "date":"7/2",
      "day":7,
      "month":2,
      "prayers":{
        "fajr":"4:55",
        "sunrise":"6:14",
        "dhuhr":"11:48",
        "asr":"14:59",
        "maghrib":"17:24",
        "isha":"18:54"
      }
    },
    {
      "date":"8/2",
      "day":8,
      "month":2,
      "prayers":{
        "fajr":"4:55",
        "sunrise":"6:13",
        "dhuhr":"11:48",
        "asr":"14:59",
        "maghrib":"17:25",
        "isha":"18:55"
      }
    },
    {
      "date":"9/2",
      "day":9,
      "month":2,
      "prayers":{
        "fajr":"4:54",
        "sunrise":"6:13",
        "dhuhr":"11:48",
        "asr":"15:00",
        "maghrib":"17:26",
        "isha":"18:56"
      }
    },
    {
      "date":"10/2",
      "day":10,
      "month":2,
      "prayers":{
        "fajr":"4:54",
        "sunrise":"6:12",
        "dhuhr":"11:48",
        "asr":"15:00",
        "maghrib":"17:26",
        "isha":"18:56"
      }
    },
    {
      "date":"11/2",
      "day":11,
      "month":2,
      "prayers":{
        "fajr":"4:53",
        "sunrise":"6:12",
        "dhuhr":"11:48",
        "asr":"15:01",
        "maghrib":"17:27",
        "isha":"18:57"
      }
    },
    {
      "date":"12/2",
      "day":12,
      "month":2,
      "prayers":{
        "fajr":"4:52",
        "sunrise":"6:11",
        "dhuhr":"11:48",
        "asr":"15:01",
        "maghrib":"17:28",
        "isha":"18:58"
      }
    },
    {
      "date":"13/2",
      "day":13,
      "month":2,
      "prayers":{
        "fajr":"4:52",
        "sunrise":"6:10",
        "dhuhr":"11:48",
        "asr":"15:02",
        "maghrib":"17:28",
        "isha":"18:58"
      }
    },
    {
      "date":"14/2",
      "day":14,
      "month":2,
      "prayers":{
        "fajr":"4:51",
        "sunrise":"6:09",
        "dhuhr":"11:48",
        "asr":"15:02",
        "maghrib":"17:29",
        "isha":"18:59"
      }
    },
    {
      "date":"15/2",
      "day":15,
      "month":2,
      "prayers":{
        "fajr":"4:51",
        "sunrise":"6:09",
        "dhuhr":"11:48",
        "asr":"15:03",
        "maghrib":"17:30",
        "isha":"19:00"
      }
    },
    {
      "date":"16/2",
      "day":16,
      "month":2,
      "prayers":{
        "fajr":"4:50",
        "sunrise":"6:08",
        "dhuhr":"11:48",
        "asr":"15:03",
        "maghrib":"17:30",
        "isha":"19:00"
      }
    },
    {
      "date":"17/2",
      "day":17,
      "month":2,
      "prayers":{
        "fajr":"4:49",
        "sunrise":"6:07",
        "dhuhr":"11:48",
        "asr":"15:03",
        "maghrib":"17:31",
        "isha":"19:01"
      }
    },
    {
      "date":"18/2",
      "day":18,
      "month":2,
      "prayers":{
        "fajr":"4:49",
        "sunrise":"6:07",
        "dhuhr":"11:48",
        "asr":"15:04",
        "maghrib":"17:31",
        "isha":"19:01"
      }
    },
    {
      "date":"19/2",
      "day":19,
      "month":2,
      "prayers":{
        "fajr":"4:48",
        "sunrise":"6:06",
        "dhuhr":"11:48",
        "asr":"15:04",
        "maghrib":"17:32",
        "isha":"19:02"
      }
    },
    {
      "date":"20/2",
      "day":20,
      "month":2,
      "prayers":{
        "fajr":"4:47",
        "sunrise":"6:05",
        "dhuhr":"11:48",
        "asr":"15:04",
        "maghrib":"17:33",
        "isha":"19:03"
      }
    },
    {
      "date":"21/2",
      "day":21,
      "month":2,
      "prayers":{
        "fajr":"4:47",
        "sunrise":"6:04",
        "dhuhr":"11:48",
        "asr":"15:05",
        "maghrib":"17:33",
        "isha":"19:03"
      }
    },
    {
      "date":"22/2",
      "day":22,
      "month":2,
      "prayers":{
        "fajr":"4:46",
        "sunrise":"6:03",
        "dhuhr":"11:47",
        "asr":"15:05",
        "maghrib":"17:34",
        "isha":"19:04"
      }
    },
    {
      "date":"23/2",
      "day":23,
      "month":2,
      "prayers":{
        "fajr":"4:45",
        "sunrise":"6:02",
        "dhuhr":"11:47",
        "asr":"15:05",
        "maghrib":"17:34",
        "isha":"19:04"
      }
    },
    {
      "date":"24/2",
      "day":24,
      "month":2,
      "prayers":{
        "fajr":"4:44",
        "sunrise":"6:02",
        "dhuhr":"11:47",
        "asr":"15:05",
        "maghrib":"17:35",
        "isha":"19:05"
      }
    },
    {
      "date":"25/2",
      "day":25,
      "month":2,
      "prayers":{
        "fajr":"4:43",
        "sunrise":"6:01",
        "dhuhr":"11:47",
        "asr":"15:06",
        "maghrib":"17:36",
        "isha":"19:06"
      }
    },
    {
      "date":"26/2",
      "day":26,
      "month":2,
      "prayers":{
        "fajr":"4:43",
        "sunrise":"6:00",
        "dhuhr":"11:47",
        "asr":"15:06",
        "maghrib":"17:36",
        "isha":"19:06"
      }
    },
    {
      "date":"27/2",
      "day":27,
      "month":2,
      "prayers":{
        "fajr":"4:42",
        "sunrise":"5:59",
        "dhuhr":"11:47",
        "asr":"15:06",
        "maghrib":"17:37",
        "isha":"19:07"
      }
    },
    {
      "date":"28/2",
      "day":28,
      "month":2,
      "prayers":{
        "fajr":"4:41",
        "sunrise":"5:58",
        "dhuhr":"11:46",
        "asr":"15:06",
        "maghrib":"17:37",
        "isha":"19:07"
      }
    },
    {
      "date":"1/3",
      "day":1,
      "month":3,
      "prayers":{
        "fajr":"4:40",
        "sunrise":"5:57",
        "dhuhr":"11:46",
        "asr":"15:07",
        "maghrib":"17:38",
        "isha":"19:08"
      }
    },
    {
      "date":"2/3",
      "day":2,
      "month":3,
      "prayers":{
        "fajr":"4:39",
        "sunrise":"5:56",
        "dhuhr":"11:46",
        "asr":"15:07",
        "maghrib":"17:38",
        "isha":"19:08"
      }
    },
    {
      "date":"3/3",
      "day":3,
      "month":3,
      "prayers":{
        "fajr":"4:38",
        "sunrise":"5:55",
        "dhuhr":"11:46",
        "asr":"15:07",
        "maghrib":"17:39",
        "isha":"19:09"
      }
    },
    {
      "date":"4/3",
      "day":4,
      "month":3,
      "prayers":{
        "fajr":"4:37",
        "sunrise":"5:54",
        "dhuhr":"11:46",
        "asr":"15:07",
        "maghrib":"17:39",
        "isha":"19:09"
      }
    },
    {
      "date":"5/3",
      "day":5,
      "month":3,
      "prayers":{
        "fajr":"4:36",
        "sunrise":"5:53",
        "dhuhr":"11:45",
        "asr":"15:07",
        "maghrib":"17:40",
        "isha":"19:10"
      }
    },
    {
      "date":"6/3",
      "day":6,
      "month":3,
      "prayers":{
        "fajr":"4:35",
        "sunrise":"5:52",
        "dhuhr":"11:45",
        "asr":"15:07",
        "maghrib":"17:40",
        "isha":"19:10"
      }
    },
    {
      "date":"7/3",
      "day":7,
      "month":3,
      "prayers":{
        "fajr":"4:35",
        "sunrise":"5:51",
        "dhuhr":"11:45",
        "asr":"15:07",
        "maghrib":"17:41",
        "isha":"19:11"
      }
    },
    {
      "date":"8/3",
      "day":8,
      "month":3,
      "prayers":{
        "fajr":"4:34",
        "sunrise":"5:51",
        "dhuhr":"11:45",
        "asr":"15:08",
        "maghrib":"17:41",
        "isha":"19:11"
      }
    },
    {
      "date":"9/3",
      "day":9,
      "month":3,
      "prayers":{
        "fajr":"4:33",
        "sunrise":"5:50",
        "dhuhr":"11:44",
        "asr":"15:08",
        "maghrib":"17:42",
        "isha":"19:12"
      }
    },
    {
      "date":"10/3",
      "day":10,
      "month":3,
      "prayers":{
        "fajr":"4:32",
        "sunrise":"5:49",
        "dhuhr":"11:44",
        "asr":"15:08",
        "maghrib":"17:42",
        "isha":"19:12"
      }
    },
    {
      "date":"11/3",
      "day":11,
      "month":3,
      "prayers":{
        "fajr":"4:31",
        "sunrise":"5:48",
        "dhuhr":"11:44",
        "asr":"15:08",
        "maghrib":"17:43",
        "isha":"19:13"
      }
    },
    {
      "date":"12/3",
      "day":12,
      "month":3,
      "prayers":{
        "fajr":"4:30",
        "sunrise":"5:47",
        "dhuhr":"11:44",
        "asr":"15:08",
        "maghrib":"17:43",
        "isha":"19:13"
      }
    },
    {
      "date":"13/3",
      "day":13,
      "month":3,
      "prayers":{
        "fajr":"4:29",
        "sunrise":"5:46",
        "dhuhr":"11:43",
        "asr":"15:08",
        "maghrib":"17:44",
        "isha":"19:14"
      }
    },
    {
      "date":"14/3",
      "day":14,
      "month":3,
      "prayers":{
        "fajr":"4:28",
        "sunrise":"5:44",
        "dhuhr":"11:43",
        "asr":"15:08",
        "maghrib":"17:44",
        "isha":"19:14"
      }
    },
    {
      "date":"15/3",
      "day":15,
      "month":3,
      "prayers":{
        "fajr":"4:26",
        "sunrise":"5:43",
        "dhuhr":"11:43",
        "asr":"15:08",
        "maghrib":"17:45",
        "isha":"19:15"
      }
    },
    {
      "date":"16/3",
      "day":16,
      "month":3,
      "prayers":{
        "fajr":"4:25",
        "sunrise":"5:42",
        "dhuhr":"11:43",
        "asr":"15:08",
        "maghrib":"17:45",
        "isha":"19:15"
      }
    },
    {
      "date":"17/3",
      "day":17,
      "month":3,
      "prayers":{
        "fajr":"4:24",
        "sunrise":"5:41",
        "dhuhr":"11:42",
        "asr":"15:08",
        "maghrib":"17:46",
        "isha":"19:16"
      }
    },
    {
      "date":"18/3",
      "day":18,
      "month":3,
      "prayers":{
        "fajr":"4:23",
        "sunrise":"5:40",
        "dhuhr":"11:42",
        "asr":"15:08",
        "maghrib":"17:46",
        "isha":"19:16"
      }
    },
    {
      "date":"19/3",
      "day":19,
      "month":3,
      "prayers":{
        "fajr":"4:22",
        "sunrise":"5:39",
        "dhuhr":"11:42",
        "asr":"15:08",
        "maghrib":"17:46",
        "isha":"19:16"
      }
    },
    {
      "date":"20/3",
      "day":20,
      "month":3,
      "prayers":{
        "fajr":"4:21",
        "sunrise":"5:38",
        "dhuhr":"11:41",
        "asr":"15:08",
        "maghrib":"17:47",
        "isha":"19:17"
      }
    },
    {
      "date":"21/3",
      "day":21,
      "month":3,
      "prayers":{
        "fajr":"4:20",
        "sunrise":"5:37",
        "dhuhr":"11:41",
        "asr":"15:08",
        "maghrib":"17:47",
        "isha":"19:17"
      }
    },
    {
      "date":"22/3",
      "day":22,
      "month":3,
      "prayers":{
        "fajr":"4:19",
        "sunrise":"5:36",
        "dhuhr":"11:41",
        "asr":"15:08",
        "maghrib":"17:48",
        "isha":"19:18"
      }
    },
    {
      "date":"23/3",
      "day":23,
      "month":3,
      "prayers":{
        "fajr":"4:18",
        "sunrise":"5:35",
        "dhuhr":"11:41",
        "asr":"15:08",
        "maghrib":"17:49",
        "isha":"19:19"
      }
    },
    {
      "date":"24/3",
      "day":24,
      "month":3,
      "prayers":{
        "fajr":"4:17",
        "sunrise":"5:34",
        "dhuhr":"11:40",
        "asr":"15:07",
        "maghrib":"17:50",
        "isha":"19:20"
      }
    },
    {
      "date":"25/3",
      "day":25,
      "month":3,
      "prayers":{
        "fajr":"4:16",
        "sunrise":"5:33",
        "dhuhr":"11:40",
        "asr":"15:07",
        "maghrib":"17:50",
        "isha":"19:20"
      }
    },
    {
      "date":"26/3",
      "day":26,
      "month":3,
      "prayers":{
        "fajr":"4:15",
        "sunrise":"5:32",
        "dhuhr":"11:40",
        "asr":"15:07",
        "maghrib":"17:51",
        "isha":"19:21"
      }
    },
    {
      "date":"27/3",
      "day":27,
      "month":3,
      "prayers":{
        "fajr":"4:13",
        "sunrise":"5:31",
        "dhuhr":"11:39",
        "asr":"15:07",
        "maghrib":"17:51",
        "isha":"19:21"
      }
    },
    {
      "date":"28/3",
      "day":28,
      "month":3,
      "prayers":{
        "fajr":"4:12",
        "sunrise":"5:30",
        "dhuhr":"11:39",
        "asr":"15:07",
        "maghrib":"17:51",
        "isha":"19:21"
      }
    },
    {
      "date":"29/3",
      "day":29,
      "month":3,
      "prayers":{
        "fajr":"4:11",
        "sunrise":"5:29",
        "dhuhr":"11:39",
        "asr":"15:07",
        "maghrib":"17:52",
        "isha":"19:22"
      }
    },
    {
      "date":"30/3",
      "day":30,
      "month":3,
      "prayers":{
        "fajr":"4:10",
        "sunrise":"5:28",
        "dhuhr":"11:38",
        "asr":"15:07",
        "maghrib":"17:52",
        "isha":"19:22"
      }
    },
    {
      "date":"31/3",
      "day":31,
      "month":3,
      "prayers":{
        "fajr":"4:09",
        "sunrise":"5:27",
        "dhuhr":"11:38",
        "asr":"15:07",
        "maghrib":"17:53",
        "isha":"19:23"
      }
    },
    {
      "date":"1/4",
      "day":1,
      "month":4,
      "prayers":{
        "fajr":"4:08",
        "sunrise":"5:26",
        "dhuhr":"11:38",
        "asr":"15:06",
        "maghrib":"17:53",
        "isha":"19:23"
      }
    },
    {
      "date":"2/4",
      "day":2,
      "month":4,
      "prayers":{
        "fajr":"4:07",
        "sunrise":"5:25",
        "dhuhr":"11:38",
        "asr":"15:06",
        "maghrib":"17:54",
        "isha":"19:24"
      }
    },
    {
      "date":"3/4",
      "day":3,
      "month":4,
      "prayers":{
        "fajr":"4:05",
        "sunrise":"5:24",
        "dhuhr":"11:37",
        "asr":"15:06",
        "maghrib":"17:54",
        "isha":"19:24"
      }
    },
    {
      "date":"4/4",
      "day":4,
      "month":4,
      "prayers":{
        "fajr":"4:04",
        "sunrise":"5:23",
        "dhuhr":"11:37",
        "asr":"15:06",
        "maghrib":"17:55",
        "isha":"19:25"
      }
    },
    {
      "date":"5/4",
      "day":5,
      "month":4,
      "prayers":{
        "fajr":"4:03",
        "sunrise":"5:22",
        "dhuhr":"11:37",
        "asr":"15:06",
        "maghrib":"17:55",
        "isha":"19:25"
      }
    },
    {
      "date":"6/4",
      "day":6,
      "month":4,
      "prayers":{
        "fajr":"4:02",
        "sunrise":"5:21",
        "dhuhr":"11:36",
        "asr":"15:06",
        "maghrib":"17:55",
        "isha":"19:25"
      }
    },
    {
      "date":"7/4",
      "day":7,
      "month":4,
      "prayers":{
        "fajr":"4:01",
        "sunrise":"5:20",
        "dhuhr":"11:36",
        "asr":"15:05",
        "maghrib":"17:56",
        "isha":"19:26"
      }
    },
    {
      "date":"8/4",
      "day":8,
      "month":4,
      "prayers":{
        "fajr":"4:00",
        "sunrise":"5:19",
        "dhuhr":"11:36",
        "asr":"15:05",
        "maghrib":"17:56",
        "isha":"19:26"
      }
    },
    {
      "date":"9/4",
      "day":9,
      "month":4,
      "prayers":{
        "fajr":"3:59",
        "sunrise":"5:18",
        "dhuhr":"11:36",
        "asr":"15:05",
        "maghrib":"17:57",
        "isha":"19:27"
      }
    },
    {
      "date":"10/4",
      "day":10,
      "month":4,
      "prayers":{
        "fajr":"3:58",
        "sunrise":"5:17",
        "dhuhr":"11:35",
        "asr":"15:05",
        "maghrib":"17:57",
        "isha":"19:27"
      }
    },
    {
      "date":"11/4",
      "day":11,
      "month":4,
      "prayers":{
        "fajr":"3:56",
        "sunrise":"5:16",
        "dhuhr":"11:35",
        "asr":"15:04",
        "maghrib":"17:58",
        "isha":"19:28"
      }
    },
    {
      "date":"12/4",
      "day":12,
      "month":4,
      "prayers":{
        "fajr":"3:55",
        "sunrise":"5:15",
        "dhuhr":"11:35",
        "asr":"15:04",
        "maghrib":"17:58",
        "isha":"19:28"
      }
    },
    {
      "date":"13/4",
      "day":13,
      "month":4,
      "prayers":{
        "fajr":"3:54",
        "sunrise":"5:14",
        "dhuhr":"11:34",
        "asr":"15:04",
        "maghrib":"17:59",
        "isha":"19:29"
      }
    },
    {
      "date":"14/4",
      "day":14,
      "month":4,
      "prayers":{
        "fajr":"3:53",
        "sunrise":"5:13",
        "dhuhr":"11:34",
        "asr":"15:04",
        "maghrib":"17:59",
        "isha":"19:29"
      }
    },
    {
      "date":"15/4",
      "day":15,
      "month":4,
      "prayers":{
        "fajr":"3:52",
        "sunrise":"5:12",
        "dhuhr":"11:34",
        "asr":"15:04",
        "maghrib":"17:59",
        "isha":"19:29"
      }
    },
    {
      "date":"16/4",
      "day":16,
      "month":4,
      "prayers":{
        "fajr":"3:51",
        "sunrise":"5:11",
        "dhuhr":"11:34",
        "asr":"15:03",
        "maghrib":"18:00",
        "isha":"19:30"
      }
    },
    {
      "date":"17/4",
      "day":17,
      "month":4,
      "prayers":{
        "fajr":"3:50",
        "sunrise":"5:10",
        "dhuhr":"11:33",
        "asr":"15:03",
        "maghrib":"18:00",
        "isha":"19:30"
      }
    },
    {
      "date":"18/4",
      "day":18,
      "month":4,
      "prayers":{
        "fajr":"3:49",
        "sunrise":"5:09",
        "dhuhr":"11:33",
        "asr":"15:03",
        "maghrib":"18:01",
        "isha":"19:31"
      }
    },
    {
      "date":"19/4",
      "day":19,
      "month":4,
      "prayers":{
        "fajr":"3:48",
        "sunrise":"5:08",
        "dhuhr":"11:33",
        "asr":"15:03",
        "maghrib":"18:01",
        "isha":"19:31"
      }
    },
    {
      "date":"20/4",
      "day":20,
      "month":4,
      "prayers":{
        "fajr":"3:46",
        "sunrise":"5:07",
        "dhuhr":"11:33",
        "asr":"15:02",
        "maghrib":"18:02",
        "isha":"19:32"
      }
    },
    {
      "date":"21/4",
      "day":21,
      "month":4,
      "prayers":{
        "fajr":"3:45",
        "sunrise":"5:06",
        "dhuhr":"11:33",
        "asr":"15:02",
        "maghrib":"18:01",
        "isha":"19:31"
      }
    },
    {
      "date":"22/4",
      "day":22,
      "month":4,
      "prayers":{
        "fajr":"3:44",
        "sunrise":"5:05",
        "dhuhr":"11:32",
        "asr":"15:02",
        "maghrib":"18:02",
        "isha":"19:32"
      }
    },
    {
      "date":"23/4",
      "day":23,
      "month":4,
      "prayers":{
        "fajr":"3:43",
        "sunrise":"5:05",
        "dhuhr":"11:32",
        "asr":"15:02",
        "maghrib":"18:02",
        "isha":"19:32"
      }
    },
    {
      "date":"24/4",
      "day":24,
      "month":4,
      "prayers":{
        "fajr":"3:42",
        "sunrise":"5:04",
        "dhuhr":"11:32",
        "asr":"15:01",
        "maghrib":"18:03",
        "isha":"19:33"
      }
    },
    {
      "date":"25/4",
      "day":25,
      "month":4,
      "prayers":{
        "fajr":"3:41",
        "sunrise":"5:03",
        "dhuhr":"11:32",
        "asr":"15:01",
        "maghrib":"18:03",
        "isha":"19:33"
      }
    },
    {
      "date":"26/4",
      "day":26,
      "month":4,
      "prayers":{
        "fajr":"3:40",
        "sunrise":"5:02",
        "dhuhr":"11:32",
        "asr":"15:01",
        "maghrib":"18:04",
        "isha":"19:34"
      }
    },
    {
      "date":"27/4",
      "day":27,
      "month":4,
      "prayers":{
        "fajr":"3:39",
        "sunrise":"5:01",
        "dhuhr":"11:32",
        "asr":"15:01",
        "maghrib":"18:04",
        "isha":"19:34"
      }
    },
    {
      "date":"28/4",
      "day":28,
      "month":4,
      "prayers":{
        "fajr":"3:38",
        "sunrise":"5:00",
        "dhuhr":"11:31",
        "asr":"15:00",
        "maghrib":"18:05",
        "isha":"19:35"
      }
    },
    {
      "date":"29/4",
      "day":29,
      "month":4,
      "prayers":{
        "fajr":"3:37",
        "sunrise":"5:00",
        "dhuhr":"11:31",
        "asr":"15:00",
        "maghrib":"18:05",
        "isha":"19:35"
      }
    },
    {
      "date":"30/4",
      "day":30,
      "month":4,
      "prayers":{
        "fajr":"3:36",
        "sunrise":"4:59",
        "dhuhr":"11:31",
        "asr":"15:00",
        "maghrib":"18:06",
        "isha":"19:36"
      }
    },
    {
      "date":"1/5",
      "day":1,
      "month":5,
      "prayers":{
        "fajr":"3:35",
        "sunrise":"4:58",
        "dhuhr":"11:31",
        "asr":"15:00",
        "maghrib":"18:06",
        "isha":"19:36"
      }
    },
    {
      "date":"2/5",
      "day":2,
      "month":5,
      "prayers":{
        "fajr":"3:34",
        "sunrise":"4:57",
        "dhuhr":"11:31",
        "asr":"15:00",
        "maghrib":"18:07",
        "isha":"19:37"
      }
    },
    {
      "date":"3/5",
      "day":3,
      "month":5,
      "prayers":{
        "fajr":"3:33",
        "sunrise":"4:57",
        "dhuhr":"11:31",
        "asr":"14:59",
        "maghrib":"18:07",
        "isha":"19:37"
      }
    },
    {
      "date":"4/5",
      "day":4,
      "month":5,
      "prayers":{
        "fajr":"3:32",
        "sunrise":"4:56",
        "dhuhr":"11:31",
        "asr":"14:59",
        "maghrib":"18:08",
        "isha":"19:38"
      }
    },
    {
      "date":"5/5",
      "day":5,
      "month":5,
      "prayers":{
        "fajr":"3:32",
        "sunrise":"4:55",
        "dhuhr":"11:31",
        "asr":"14:59",
        "maghrib":"18:08",
        "isha":"19:38"
      }
    },
    {
      "date":"6/5",
      "day":6,
      "month":5,
      "prayers":{
        "fajr":"3:31",
        "sunrise":"4:55",
        "dhuhr":"11:30",
        "asr":"14:59",
        "maghrib":"18:09",
        "isha":"19:39"
      }
    },
    {
      "date":"7/5",
      "day":7,
      "month":5,
      "prayers":{
        "fajr":"3:30",
        "sunrise":"4:54",
        "dhuhr":"11:30",
        "asr":"14:58",
        "maghrib":"18:09",
        "isha":"19:39"
      }
    },
    {
      "date":"8/5",
      "day":8,
      "month":5,
      "prayers":{
        "fajr":"3:29",
        "sunrise":"4:53",
        "dhuhr":"11:30",
        "asr":"14:58",
        "maghrib":"18:10",
        "isha":"19:40"
      }
    },
    {
      "date":"9/5",
      "day":9,
      "month":5,
      "prayers":{
        "fajr":"3:28",
        "sunrise":"4:53",
        "dhuhr":"11:30",
        "asr":"14:58",
        "maghrib":"18:10",
        "isha":"19:40"
      }
    },
    {
      "date":"10/5",
      "day":10,
      "month":5,
      "prayers":{
        "fajr":"3:27",
        "sunrise":"4:52",
        "dhuhr":"11:30",
        "asr":"14:58",
        "maghrib":"18:11",
        "isha":"19:41"
      }
    },
    {
      "date":"11/5",
      "day":11,
      "month":5,
      "prayers":{
        "fajr":"3:26",
        "sunrise":"4:51",
        "dhuhr":"11:30",
        "asr":"14:58",
        "maghrib":"18:11",
        "isha":"19:41"
      }
    },
    {
      "date":"12/5",
      "day":12,
      "month":5,
      "prayers":{
        "fajr":"3:26",
        "sunrise":"4:51",
        "dhuhr":"11:30",
        "asr":"14:57",
        "maghrib":"18:12",
        "isha":"19:42"
      }
    },
    {
      "date":"13/5",
      "day":13,
      "month":5,
      "prayers":{
        "fajr":"3:25",
        "sunrise":"4:50",
        "dhuhr":"11:30",
        "asr":"14:57",
        "maghrib":"18:12",
        "isha":"19:42"
      }
    },
    {
      "date":"14/5",
      "day":14,
      "month":5,
      "prayers":{
        "fajr":"3:24",
        "sunrise":"4:50",
        "dhuhr":"11:30",
        "asr":"14:57",
        "maghrib":"18:13",
        "isha":"19:43"
      }
    },
    {
      "date":"15/5",
      "day":15,
      "month":5,
      "prayers":{
        "fajr":"3:23",
        "sunrise":"4:49",
        "dhuhr":"11:30",
        "asr":"14:57",
        "maghrib":"18:13",
        "isha":"19:43"
      }
    },
    {
      "date":"16/5",
      "day":16,
      "month":5,
      "prayers":{
        "fajr":"3:23",
        "sunrise":"4:49",
        "dhuhr":"11:30",
        "asr":"14:57",
        "maghrib":"18:14",
        "isha":"19:44"
      }
    },
    {
      "date":"17/5",
      "day":17,
      "month":5,
      "prayers":{
        "fajr":"3:22",
        "sunrise":"4:48",
        "dhuhr":"11:30",
        "asr":"14:57",
        "maghrib":"18:14",
        "isha":"19:44"
      }
    },
    {
      "date":"18/5",
      "day":18,
      "month":5,
      "prayers":{
        "fajr":"3:21",
        "sunrise":"4:48",
        "dhuhr":"11:30",
        "asr":"14:57",
        "maghrib":"18:15",
        "isha":"19:45"
      }
    },
    {
      "date":"19/5",
      "day":19,
      "month":5,
      "prayers":{
        "fajr":"3:21",
        "sunrise":"4:47",
        "dhuhr":"11:30",
        "asr":"14:56",
        "maghrib":"18:16",
        "isha":"19:46"
      }
    },
    {
      "date":"20/5",
      "day":20,
      "month":5,
      "prayers":{
        "fajr":"3:20",
        "sunrise":"4:47",
        "dhuhr":"11:30",
        "asr":"14:56",
        "maghrib":"18:16",
        "isha":"19:46"
      }
    },
    {
      "date":"21/5",
      "day":21,
      "month":5,
      "prayers":{
        "fajr":"3:20",
        "sunrise":"4:47",
        "dhuhr":"11:30",
        "asr":"14:56",
        "maghrib":"18:17",
        "isha":"19:47"
      }
    },
    {
      "date":"22/5",
      "day":22,
      "month":5,
      "prayers":{
        "fajr":"3:19",
        "sunrise":"4:46",
        "dhuhr":"11:31",
        "asr":"14:56",
        "maghrib":"18:17",
        "isha":"19:47"
      }
    },
    {
      "date":"23/5",
      "day":23,
      "month":5,
      "prayers":{
        "fajr":"3:18",
        "sunrise":"4:46",
        "dhuhr":"11:31",
        "asr":"14:56",
        "maghrib":"18:18",
        "isha":"19:48"
      }
    },
    {
      "date":"24/5",
      "day":24,
      "month":5,
      "prayers":{
        "fajr":"3:18",
        "sunrise":"4:45",
        "dhuhr":"11:31",
        "asr":"14:56",
        "maghrib":"18:18",
        "isha":"19:48"
      }
    },
    {
      "date":"25/5",
      "day":25,
      "month":5,
      "prayers":{
        "fajr":"3:17",
        "sunrise":"4:45",
        "dhuhr":"11:31",
        "asr":"14:56",
        "maghrib":"18:19",
        "isha":"19:49"
      }
    },
    {
      "date":"26/5",
      "day":26,
      "month":5,
      "prayers":{
        "fajr":"3:17",
        "sunrise":"4:45",
        "dhuhr":"11:31",
        "asr":"14:56",
        "maghrib":"18:19",
        "isha":"19:49"
      }
    },
    {
      "date":"27/5",
      "day":27,
      "month":5,
      "prayers":{
        "fajr":"3:16",
        "sunrise":"4:45",
        "dhuhr":"11:31",
        "asr":"14:56",
        "maghrib":"18:20",
        "isha":"19:50"
      }
    },
    {
      "date":"28/5",
      "day":28,
      "month":5,
      "prayers":{
        "fajr":"3:16",
        "sunrise":"4:44",
        "dhuhr":"11:31",
        "asr":"14:56",
        "maghrib":"18:20",
        "isha":"19:50"
      }
    },
    {
      "date":"29/5",
      "day":29,
      "month":5,
      "prayers":{
        "fajr":"3:16",
        "sunrise":"4:44",
        "dhuhr":"11:31",
        "asr":"14:56",
        "maghrib":"18:21",
        "isha":"19:51"
      }
    },
    {
      "date":"30/5",
      "day":30,
      "month":5,
      "prayers":{
        "fajr":"3:15",
        "sunrise":"4:44",
        "dhuhr":"11:31",
        "asr":"14:56",
        "maghrib":"18:21",
        "isha":"19:51"
      }
    },
    {
      "date":"31/5",
      "day":31,
      "month":5,
      "prayers":{
        "fajr":"3:15",
        "sunrise":"4:44",
        "dhuhr":"11:32",
        "asr":"14:56",
        "maghrib":"18:21",
        "isha":"19:51"
      }
    },
    {
      "date":"1/6",
      "day":1,
      "month":6,
      "prayers":{
        "fajr":"3:15",
        "sunrise":"4:44",
        "dhuhr":"11:32",
        "asr":"14:56",
        "maghrib":"18:22",
        "isha":"19:52"
      }
    },
    {
      "date":"2/6",
      "day":2,
      "month":6,
      "prayers":{
        "fajr":"3:14",
        "sunrise":"4:43",
        "dhuhr":"11:32",
        "asr":"14:56",
        "maghrib":"18:22",
        "isha":"19:52"
      }
    },
    {
      "date":"3/6",
      "day":3,
      "month":6,
      "prayers":{
        "fajr":"3:14",
        "sunrise":"4:43",
        "dhuhr":"11:32",
        "asr":"14:56",
        "maghrib":"18:23",
        "isha":"19:53"
      }
    },
    {
      "date":"4/6",
      "day":4,
      "month":6,
      "prayers":{
        "fajr":"3:14",
        "sunrise":"4:43",
        "dhuhr":"11:32",
        "asr":"14:56",
        "maghrib":"18:23",
        "isha":"19:53"
      }
    },
    {
      "date":"5/6",
      "day":5,
      "month":6,
      "prayers":{
        "fajr":"3:13",
        "sunrise":"4:43",
        "dhuhr":"11:32",
        "asr":"14:56",
        "maghrib":"18:24",
        "isha":"19:54"
      }
    },
    {
      "date":"6/6",
      "day":6,
      "month":6,
      "prayers":{
        "fajr":"3:13",
        "sunrise":"4:43",
        "dhuhr":"11:32",
        "asr":"14:56",
        "maghrib":"18:24",
        "isha":"19:54"
      }
    },
    {
      "date":"7/6",
      "day":7,
      "month":6,
      "prayers":{
        "fajr":"3:13",
        "sunrise":"4:43",
        "dhuhr":"11:33",
        "asr":"14:56",
        "maghrib":"18:25",
        "isha":"19:55"
      }
    },
    {
      "date":"8/6",
      "day":8,
      "month":6,
      "prayers":{
        "fajr":"3:13",
        "sunrise":"4:43",
        "dhuhr":"11:33",
        "asr":"14:56",
        "maghrib":"18:25",
        "isha":"19:55"
      }
    },
    {
      "date":"9/6",
      "day":9,
      "month":6,
      "prayers":{
        "fajr":"3:13",
        "sunrise":"4:43",
        "dhuhr":"11:33",
        "asr":"14:56",
        "maghrib":"18:25",
        "isha":"19:55"
      }
    },
    {
      "date":"10/6",
      "day":10,
      "month":6,
      "prayers":{
        "fajr":"3:13",
        "sunrise":"4:43",
        "dhuhr":"11:33",
        "asr":"14:56",
        "maghrib":"18:26",
        "isha":"19:56"
      }
    },
    {
      "date":"11/6",
      "day":11,
      "month":6,
      "prayers":{
        "fajr":"3:13",
        "sunrise":"4:43",
        "dhuhr":"11:33",
        "asr":"14:57",
        "maghrib":"18:26",
        "isha":"19:56"
      }
    },
    {
      "date":"12/6",
      "day":12,
      "month":6,
      "prayers":{
        "fajr":"3:13",
        "sunrise":"4:43",
        "dhuhr":"11:34",
        "asr":"14:57",
        "maghrib":"18:26",
        "isha":"19:56"
      }
    },
    {
      "date":"13/6",
      "day":13,
      "month":6,
      "prayers":{
        "fajr":"3:13",
        "sunrise":"4:43",
        "dhuhr":"11:34",
        "asr":"14:57",
        "maghrib":"18:27",
        "isha":"19:57"
      }
    },
    {
      "date":"14/6",
      "day":14,
      "month":6,
      "prayers":{
        "fajr":"3:13",
        "sunrise":"4:43",
        "dhuhr":"11:34",
        "asr":"14:57",
        "maghrib":"18:27",
        "isha":"19:57"
      }
    },
    {
      "date":"15/6",
      "day":15,
      "month":6,
      "prayers":{
        "fajr":"3:13",
        "sunrise":"4:43",
        "dhuhr":"11:34",
        "asr":"14:57",
        "maghrib":"18:27",
        "isha":"19:57"
      }
    },
    {
      "date":"16/6",
      "day":16,
      "month":6,
      "prayers":{
        "fajr":"3:13",
        "sunrise":"4:43",
        "dhuhr":"11:35",
        "asr":"14:57",
        "maghrib":"18:28",
        "isha":"19:58"
      }
    },
    {
      "date":"17/6",
      "day":17,
      "month":6,
      "prayers":{
        "fajr":"3:13",
        "sunrise":"4:43",
        "dhuhr":"11:35",
        "asr":"14:57",
        "maghrib":"18:28",
        "isha":"19:58"
      }
    },
    {
      "date":"18/6",
      "day":18,
      "month":6,
      "prayers":{
        "fajr":"3:13",
        "sunrise":"4:44",
        "dhuhr":"11:35",
        "asr":"14:58",
        "maghrib":"18:28",
        "isha":"19:58"
      }
    },
    {
      "date":"19/6",
      "day":19,
      "month":6,
      "prayers":{
        "fajr":"3:13",
        "sunrise":"4:44",
        "dhuhr":"11:35",
        "asr":"14:58",
        "maghrib":"18:29",
        "isha":"19:59"
      }
    },
    {
      "date":"20/6",
      "day":20,
      "month":6,
      "prayers":{
        "fajr":"3:13",
        "sunrise":"4:44",
        "dhuhr":"11:35",
        "asr":"14:58",
        "maghrib":"18:29",
        "isha":"19:59"
      }
    },
    {
      "date":"21/6",
      "day":21,
      "month":6,
      "prayers":{
        "fajr":"3:13",
        "sunrise":"4:44",
        "dhuhr":"11:36",
        "asr":"14:58",
        "maghrib":"18:29",
        "isha":"19:59"
      }
    },
    {
      "date":"22/6",
      "day":22,
      "month":6,
      "prayers":{
        "fajr":"3:14",
        "sunrise":"4:44",
        "dhuhr":"11:36",
        "asr":"14:58",
        "maghrib":"18:29",
        "isha":"19:59"
      }
    },
    {
      "date":"23/6",
      "day":23,
      "month":6,
      "prayers":{
        "fajr":"3:14",
        "sunrise":"4:45",
        "dhuhr":"11:36",
        "asr":"14:59",
        "maghrib":"18:29",
        "isha":"19:59"
      }
    },
    {
      "date":"24/6",
      "day":24,
      "month":6,
      "prayers":{
        "fajr":"3:14",
        "sunrise":"4:45",
        "dhuhr":"11:36",
        "asr":"14:59",
        "maghrib":"18:30",
        "isha":"20:00"
      }
    },
    {
      "date":"25/6",
      "day":25,
      "month":6,
      "prayers":{
        "fajr":"3:14",
        "sunrise":"4:45",
        "dhuhr":"11:36",
        "asr":"14:59",
        "maghrib":"18:30",
        "isha":"20:00"
      }
    },
    {
      "date":"26/6",
      "day":26,
      "month":6,
      "prayers":{
        "fajr":"3:15",
        "sunrise":"4:45",
        "dhuhr":"11:37",
        "asr":"14:59",
        "maghrib":"18:30",
        "isha":"20:00"
      }
    },
    {
      "date":"27/6",
      "day":27,
      "month":6,
      "prayers":{
        "fajr":"3:15",
        "sunrise":"4:46",
        "dhuhr":"11:37",
        "asr":"15:00",
        "maghrib":"18:30",
        "isha":"20:00"
      }
    },
    {
      "date":"28/6",
      "day":28,
      "month":6,
      "prayers":{
        "fajr":"3:15",
        "sunrise":"4:46",
        "dhuhr":"11:37",
        "asr":"15:00",
        "maghrib":"18:30",
        "isha":"20:00"
      }
    },
    {
      "date":"29/6",
      "day":29,
      "month":6,
      "prayers":{
        "fajr":"3:16",
        "sunrise":"4:46",
        "dhuhr":"11:37",
        "asr":"15:00",
        "maghrib":"18:30",
        "isha":"20:00"
      }
    },
    {
      "date":"30/6",
      "day":30,
      "month":6,
      "prayers":{
        "fajr":"3:16",
        "sunrise":"4:47",
        "dhuhr":"11:37",
        "asr":"15:00",
        "maghrib":"18:30",
        "isha":"20:00"
      }
    },
    {
      "date":"1/7",
      "day":1,
      "month":7,
      "prayers":{
        "fajr":"3:17",
        "sunrise":"4:47",
        "dhuhr":"11:38",
        "asr":"15:01",
        "maghrib":"18:30",
        "isha":"20:00"
      }
    },
    {
      "date":"2/7",
      "day":2,
      "month":7,
      "prayers":{
        "fajr":"3:17",
        "sunrise":"4:47",
        "dhuhr":"11:38",
        "asr":"15:01",
        "maghrib":"18:30",
        "isha":"20:00"
      }
    },
    {
      "date":"3/7",
      "day":3,
      "month":7,
      "prayers":{
        "fajr":"3:18",
        "sunrise":"4:48",
        "dhuhr":"11:38",
        "asr":"15:01",
        "maghrib":"18:30",
        "isha":"20:00"
      }
    },
    {
      "date":"4/7",
      "day":4,
      "month":7,
      "prayers":{
        "fajr":"3:18",
        "sunrise":"4:48",
        "dhuhr":"11:38",
        "asr":"15:02",
        "maghrib":"18:30",
        "isha":"20:00"
      }
    },
    {
      "date":"5/7",
      "day":5,
      "month":7,
      "prayers":{
        "fajr":"3:18",
        "sunrise":"4:48",
        "dhuhr":"11:38",
        "asr":"15:02",
        "maghrib":"18:30",
        "isha":"20:00"
      }
    },
    {
      "date":"6/7",
      "day":6,
      "month":7,
      "prayers":{
        "fajr":"3:19",
        "sunrise":"4:49",
        "dhuhr":"11:39",
        "asr":"15:02",
        "maghrib":"18:30",
        "isha":"20:00"
      }
    },
    {
      "date":"7/7",
      "day":7,
      "month":7,
      "prayers":{
        "fajr":"3:20",
        "sunrise":"4:49",
        "dhuhr":"11:39",
        "asr":"15:02",
        "maghrib":"18:30",
        "isha":"20:00"
      }
    },
    {
      "date":"8/7",
      "day":8,
      "month":7,
      "prayers":{
        "fajr":"3:20",
        "sunrise":"4:50",
        "dhuhr":"11:39",
        "asr":"15:03",
        "maghrib":"18:30",
        "isha":"20:00"
      }
    },
    {
      "date":"9/7",
      "day":9,
      "month":7,
      "prayers":{
        "fajr":"3:21",
        "sunrise":"4:50",
        "dhuhr":"11:39",
        "asr":"15:03",
        "maghrib":"18:30",
        "isha":"20:00"
      }
    },
    {
      "date":"10/7",
      "day":10,
      "month":7,
      "prayers":{
        "fajr":"3:21",
        "sunrise":"4:51",
        "dhuhr":"11:39",
        "asr":"15:03",
        "maghrib":"18:30",
        "isha":"20:00"
      }
    },
    {
      "date":"11/7",
      "day":11,
      "month":7,
      "prayers":{
        "fajr":"3:22",
        "sunrise":"4:51",
        "dhuhr":"11:39",
        "asr":"15:03",
        "maghrib":"18:30",
        "isha":"20:00"
      }
    },
    {
      "date":"12/7",
      "day":12,
      "month":7,
      "prayers":{
        "fajr":"3:22",
        "sunrise":"4:51",
        "dhuhr":"11:39",
        "asr":"15:04",
        "maghrib":"18:29",
        "isha":"19:59"
      }
    },
    {
      "date":"13/7",
      "day":13,
      "month":7,
      "prayers":{
        "fajr":"3:23",
        "sunrise":"4:52",
        "dhuhr":"11:40",
        "asr":"15:04",
        "maghrib":"18:29",
        "isha":"19:59"
      }
    },
    {
      "date":"14/7",
      "day":14,
      "month":7,
      "prayers":{
        "fajr":"3:24",
        "sunrise":"4:52",
        "dhuhr":"11:40",
        "asr":"15:04",
        "maghrib":"18:29",
        "isha":"19:59"
      }
    },
    {
      "date":"15/7",
      "day":15,
      "month":7,
      "prayers":{
        "fajr":"3:24",
        "sunrise":"4:53",
        "dhuhr":"11:40",
        "asr":"15:04",
        "maghrib":"18:29",
        "isha":"19:59"
      }
    },
    {
      "date":"16/7",
      "day":16,
      "month":7,
      "prayers":{
        "fajr":"3:25",
        "sunrise":"4:53",
        "dhuhr":"11:40",
        "asr":"15:05",
        "maghrib":"18:28",
        "isha":"19:58"
      }
    },
    {
      "date":"17/7",
      "day":17,
      "month":7,
      "prayers":{
        "fajr":"3:25",
        "sunrise":"4:54",
        "dhuhr":"11:40",
        "asr":"15:05",
        "maghrib":"18:28",
        "isha":"19:58"
      }
    },
    {
      "date":"18/7",
      "day":18,
      "month":7,
      "prayers":{
        "fajr":"3:26",
        "sunrise":"4:54",
        "dhuhr":"11:40",
        "asr":"15:05",
        "maghrib":"18:28",
        "isha":"19:58"
      }
    },
    {
      "date":"19/7",
      "day":19,
      "month":7,
      "prayers":{
        "fajr":"3:27",
        "sunrise":"4:55",
        "dhuhr":"11:40",
        "asr":"15:05",
        "maghrib":"18:27",
        "isha":"19:57"
      }
    },
    {
      "date":"20/7",
      "day":20,
      "month":7,
      "prayers":{
        "fajr":"3:27",
        "sunrise":"4:55",
        "dhuhr":"11:40",
        "asr":"15:06",
        "maghrib":"18:27",
        "isha":"19:57"
      }
    },
    {
      "date":"21/7",
      "day":21,
      "month":7,
      "prayers":{
        "fajr":"3:28",
        "sunrise":"4:56",
        "dhuhr":"11:40",
        "asr":"15:06",
        "maghrib":"18:27",
        "isha":"19:57"
      }
    },
    {
      "date":"22/7",
      "day":22,
      "month":7,
      "prayers":{
        "fajr":"3:29",
        "sunrise":"4:56",
        "dhuhr":"11:40",
        "asr":"15:06",
        "maghrib":"18:26",
        "isha":"19:56"
      }
    },
    {
      "date":"23/7",
      "day":23,
      "month":7,
      "prayers":{
        "fajr":"3:29",
        "sunrise":"4:56",
        "dhuhr":"11:40",
        "asr":"15:06",
        "maghrib":"18:26",
        "isha":"19:56"
      }
    },
    {
      "date":"24/7",
      "day":24,
      "month":7,
      "prayers":{
        "fajr":"3:30",
        "sunrise":"4:57",
        "dhuhr":"11:40",
        "asr":"15:06",
        "maghrib":"18:26",
        "isha":"19:56"
      }
    },
    {
      "date":"25/7",
      "day":25,
      "month":7,
      "prayers":{
        "fajr":"3:31",
        "sunrise":"4:57",
        "dhuhr":"11:40",
        "asr":"15:07",
        "maghrib":"18:25",
        "isha":"19:55"
      }
    },
    {
      "date":"26/7",
      "day":26,
      "month":7,
      "prayers":{
        "fajr":"3:31",
        "sunrise":"4:58",
        "dhuhr":"11:40",
        "asr":"15:07",
        "maghrib":"18:25",
        "isha":"19:55"
      }
    },
    {
      "date":"27/7",
      "day":27,
      "month":7,
      "prayers":{
        "fajr":"3:32",
        "sunrise":"4:58",
        "dhuhr":"11:40",
        "asr":"15:07",
        "maghrib":"18:24",
        "isha":"19:54"
      }
    },
    {
      "date":"28/7",
      "day":28,
      "month":7,
      "prayers":{
        "fajr":"3:33",
        "sunrise":"4:59",
        "dhuhr":"11:40",
        "asr":"15:07",
        "maghrib":"18:24",
        "isha":"19:54"
      }
    },
    {
      "date":"29/7",
      "day":29,
      "month":7,
      "prayers":{
        "fajr":"3:33",
        "sunrise":"4:59",
        "dhuhr":"11:40",
        "asr":"15:07",
        "maghrib":"18:23",
        "isha":"19:53"
      }
    },
    {
      "date":"30/7",
      "day":30,
      "month":7,
      "prayers":{
        "fajr":"3:34",
        "sunrise":"5:00",
        "dhuhr":"11:40",
        "asr":"15:07",
        "maghrib":"18:22",
        "isha":"19:52"
      }
    },
    {
      "date":"31/7",
      "day":31,
      "month":7,
      "prayers":{
        "fajr":"3:35",
        "sunrise":"5:00",
        "dhuhr":"11:40",
        "asr":"15:07",
        "maghrib":"18:22",
        "isha":"19:52"
      }
    },
    {
      "date":"1/8",
      "day":1,
      "month":8,
      "prayers":{
        "fajr":"3:36",
        "sunrise":"5:01",
        "dhuhr":"11:40",
        "asr":"15:07",
        "maghrib":"18:21",
        "isha":"19:51"
      }
    },
    {
      "date":"2/8",
      "day":2,
      "month":8,
      "prayers":{
        "fajr":"3:36",
        "sunrise":"5:01",
        "dhuhr":"11:40",
        "asr":"15:08",
        "maghrib":"18:21",
        "isha":"19:51"
      }
    },
    {
      "date":"3/8",
      "day":3,
      "month":8,
      "prayers":{
        "fajr":"3:37",
        "sunrise":"5:02",
        "dhuhr":"11:40",
        "asr":"15:08",
        "maghrib":"18:20",
        "isha":"19:50"
      }
    },
    {
      "date":"4/8",
      "day":4,
      "month":8,
      "prayers":{
        "fajr":"3:38",
        "sunrise":"5:02",
        "dhuhr":"11:40",
        "asr":"15:08",
        "maghrib":"18:19",
        "isha":"19:49"
      }
    },
    {
      "date":"5/8",
      "day":5,
      "month":8,
      "prayers":{
        "fajr":"3:38",
        "sunrise":"5:03",
        "dhuhr":"11:40",
        "asr":"15:08",
        "maghrib":"18:19",
        "isha":"19:49"
      }
    },
    {
      "date":"6/8",
      "day":6,
      "month":8,
      "prayers":{
        "fajr":"3:39",
        "sunrise":"5:03",
        "dhuhr":"11:40",
        "asr":"15:08",
        "maghrib":"18:18",
        "isha":"19:48"
      }
    },
    {
      "date":"7/8",
      "day":7,
      "month":8,
      "prayers":{
        "fajr":"3:40",
        "sunrise":"5:04",
        "dhuhr":"11:40",
        "asr":"15:08",
        "maghrib":"18:17",
        "isha":"19:47"
      }
    },
    {
      "date":"8/8",
      "day":8,
      "month":8,
      "prayers":{
        "fajr":"3:40",
        "sunrise":"5:04",
        "dhuhr":"11:40",
        "asr":"15:08",
        "maghrib":"18:17",
        "isha":"19:47"
      }
    },
    {
      "date":"9/8",
      "day":9,
      "month":8,
      "prayers":{
        "fajr":"3:41",
        "sunrise":"5:05",
        "dhuhr":"11:39",
        "asr":"15:08",
        "maghrib":"18:16",
        "isha":"19:46"
      }
    },
    {
      "date":"10/8",
      "day":10,
      "month":8,
      "prayers":{
        "fajr":"3:42",
        "sunrise":"5:05",
        "dhuhr":"11:39",
        "asr":"15:08",
        "maghrib":"18:15",
        "isha":"19:45"
      }
    },
    {
      "date":"11/8",
      "day":11,
      "month":8,
      "prayers":{
        "fajr":"3:42",
        "sunrise":"5:06",
        "dhuhr":"11:39",
        "asr":"15:08",
        "maghrib":"18:14",
        "isha":"19:44"
      }
    },
    {
      "date":"12/8",
      "day":12,
      "month":8,
      "prayers":{
        "fajr":"3:43",
        "sunrise":"5:06",
        "dhuhr":"11:39",
        "asr":"15:08",
        "maghrib":"18:14",
        "isha":"19:44"
      }
    },
    {
      "date":"13/8",
      "day":13,
      "month":8,
      "prayers":{
        "fajr":"3:44",
        "sunrise":"5:06",
        "dhuhr":"11:39",
        "asr":"15:08",
        "maghrib":"18:13",
        "isha":"19:43"
      }
    },
    {
      "date":"14/8",
      "day":14,
      "month":8,
      "prayers":{
        "fajr":"3:44",
        "sunrise":"5:07",
        "dhuhr":"11:39",
        "asr":"15:07",
        "maghrib":"18:12",
        "isha":"19:42"
      }
    },
    {
      "date":"15/8",
      "day":15,
      "month":8,
      "prayers":{
        "fajr":"3:45",
        "sunrise":"5:07",
        "dhuhr":"11:38",
        "asr":"15:07",
        "maghrib":"18:11",
        "isha":"19:41"
      }
    },
    {
      "date":"16/8",
      "day":16,
      "month":8,
      "prayers":{
        "fajr":"3:46",
        "sunrise":"5:08",
        "dhuhr":"11:38",
        "asr":"15:07",
        "maghrib":"18:10",
        "isha":"19:40"
      }
    },
    {
      "date":"17/8",
      "day":17,
      "month":8,
      "prayers":{
        "fajr":"3:46",
        "sunrise":"5:08",
        "dhuhr":"11:38",
        "asr":"15:07",
        "maghrib":"18:09",
        "isha":"19:39"
      }
    },
    {
      "date":"18/8",
      "day":18,
      "month":8,
      "prayers":{
        "fajr":"3:47",
        "sunrise":"5:09",
        "dhuhr":"11:38",
        "asr":"15:07",
        "maghrib":"18:09",
        "isha":"19:39"
      }
    },
    {
      "date":"19/8",
      "day":19,
      "month":8,
      "prayers":{
        "fajr":"3:47",
        "sunrise":"5:09",
        "dhuhr":"11:38",
        "asr":"15:07",
        "maghrib":"18:08",
        "isha":"19:38"
      }
    },
    {
      "date":"20/8",
      "day":20,
      "month":8,
      "prayers":{
        "fajr":"3:48",
        "sunrise":"5:09",
        "dhuhr":"11:37",
        "asr":"15:07",
        "maghrib":"18:07",
        "isha":"19:37"
      }
    },
    {
      "date":"21/8",
      "day":21,
      "month":8,
      "prayers":{
        "fajr":"3:49",
        "sunrise":"5:10",
        "dhuhr":"11:37",
        "asr":"15:06",
        "maghrib":"18:06",
        "isha":"19:36"
      }
    },
    {
      "date":"22/8",
      "day":22,
      "month":8,
      "prayers":{
        "fajr":"3:49",
        "sunrise":"5:10",
        "dhuhr":"11:37",
        "asr":"15:06",
        "maghrib":"18:05",
        "isha":"19:35"
      }
    },
    {
      "date":"23/8",
      "day":23,
      "month":8,
      "prayers":{
        "fajr":"3:50",
        "sunrise":"5:11",
        "dhuhr":"11:37",
        "asr":"15:06",
        "maghrib":"18:04",
        "isha":"19:34"
      }
    },
    {
      "date":"24/8",
      "day":24,
      "month":8,
      "prayers":{
        "fajr":"3:50",
        "sunrise":"5:11",
        "dhuhr":"11:36",
        "asr":"15:06",
        "maghrib":"18:03",
        "isha":"19:33"
      }
    },
    {
      "date":"25/8",
      "day":25,
      "month":8,
      "prayers":{
        "fajr":"3:51",
        "sunrise":"5:12",
        "dhuhr":"11:36",
        "asr":"15:05",
        "maghrib":"18:02",
        "isha":"19:32"
      }
    },
    {
      "date":"26/8",
      "day":26,
      "month":8,
      "prayers":{
        "fajr":"3:52",
        "sunrise":"5:12",
        "dhuhr":"11:36",
        "asr":"15:05",
        "maghrib":"18:01",
        "isha":"19:31"
      }
    },
    {
      "date":"27/8",
      "day":27,
      "month":8,
      "prayers":{
        "fajr":"3:52",
        "sunrise":"5:12",
        "dhuhr":"11:35",
        "asr":"15:05",
        "maghrib":"18:00",
        "isha":"19:30"
      }
    },
    {
      "date":"28/8",
      "day":28,
      "month":8,
      "prayers":{
        "fajr":"3:53",
        "sunrise":"5:13",
        "dhuhr":"11:35",
        "asr":"15:05",
        "maghrib":"17:59",
        "isha":"19:29"
      }
    },
    {
      "date":"29/8",
      "day":29,
      "month":8,
      "prayers":{
        "fajr":"3:53",
        "sunrise":"5:13",
        "dhuhr":"11:35",
        "asr":"15:04",
        "maghrib":"17:58",
        "isha":"19:28"
      }
    },
    {
      "date":"30/8",
      "day":30,
      "month":8,
      "prayers":{
        "fajr":"3:54",
        "sunrise":"5:14",
        "dhuhr":"11:35",
        "asr":"15:04",
        "maghrib":"17:57",
        "isha":"19:27"
      }
    },
    {
      "date":"31/8",
      "day":31,
      "month":8,
      "prayers":{
        "fajr":"3:54",
        "sunrise":"5:14",
        "dhuhr":"11:34",
        "asr":"15:04",
        "maghrib":"17:56",
        "isha":"19:26"
      }
    },
    {
      "date":"1/9",
      "day":1,
      "month":9,
      "prayers":{
        "fajr":"3:55",
        "sunrise":"5:14",
        "dhuhr":"11:34",
        "asr":"15:03",
        "maghrib":"17:55",
        "isha":"19:25"
      }
    },
    {
      "date":"2/9",
      "day":2,
      "month":9,
      "prayers":{
        "fajr":"3:55",
        "sunrise":"5:15",
        "dhuhr":"11:34",
        "asr":"15:03",
        "maghrib":"17:54",
        "isha":"19:24"
      }
    },
    {
      "date":"3/9",
      "day":3,
      "month":9,
      "prayers":{
        "fajr":"3:56",
        "sunrise":"5:15",
        "dhuhr":"11:33",
        "asr":"15:02",
        "maghrib":"17:53",
        "isha":"19:23"
      }
    },
    {
      "date":"4/9",
      "day":4,
      "month":9,
      "prayers":{
        "fajr":"3:56",
        "sunrise":"5:16",
        "dhuhr":"11:33",
        "asr":"15:02",
        "maghrib":"17:52",
        "isha":"19:22"
      }
    },
    {
      "date":"5/9",
      "day":5,
      "month":9,
      "prayers":{
        "fajr":"3:57",
        "sunrise":"5:16",
        "dhuhr":"11:33",
        "asr":"15:02",
        "maghrib":"17:51",
        "isha":"19:21"
      }
    },
    {
      "date":"6/9",
      "day":6,
      "month":9,
      "prayers":{
        "fajr":"3:58",
        "sunrise":"5:16",
        "dhuhr":"11:32",
        "asr":"15:01",
        "maghrib":"17:50",
        "isha":"19:20"
      }
    },
    {
      "date":"7/9",
      "day":7,
      "month":9,
      "prayers":{
        "fajr":"3:58",
        "sunrise":"5:17",
        "dhuhr":"11:32",
        "asr":"15:01",
        "maghrib":"17:49",
        "isha":"19:19"
      }
    },
    {
      "date":"8/9",
      "day":8,
      "month":9,
      "prayers":{
        "fajr":"3:59",
        "sunrise":"5:17",
        "dhuhr":"11:32",
        "asr":"15:00",
        "maghrib":"17:48",
        "isha":"19:18"
      }
    },
    {
      "date":"9/9",
      "day":9,
      "month":9,
      "prayers":{
        "fajr":"3:59",
        "sunrise":"5:17",
        "dhuhr":"11:31",
        "asr":"15:00",
        "maghrib":"17:47",
        "isha":"19:17"
      }
    },
    {
      "date":"10/9",
      "day":10,
      "month":9,
      "prayers":{
        "fajr":"3:59",
        "sunrise":"5:18",
        "dhuhr":"11:31",
        "asr":"14:59",
        "maghrib":"17:46",
        "isha":"19:16"
      }
    },
    {
      "date":"11/9",
      "day":11,
      "month":9,
      "prayers":{
        "fajr":"4:00",
        "sunrise":"5:18",
        "dhuhr":"11:31",
        "asr":"14:59",
        "maghrib":"17:45",
        "isha":"19:15"
      }
    },
    {
      "date":"12/9",
      "day":12,
      "month":9,
      "prayers":{
        "fajr":"4:00",
        "sunrise":"5:19",
        "dhuhr":"11:30",
        "asr":"14:58",
        "maghrib":"17:44",
        "isha":"19:14"
      }
    },
    {
      "date":"13/9",
      "day":13,
      "month":9,
      "prayers":{
        "fajr":"4:01",
        "sunrise":"5:19",
        "dhuhr":"11:30",
        "asr":"14:58",
        "maghrib":"17:43",
        "isha":"19:13"
      }
    },
    {
      "date":"14/9",
      "day":14,
      "month":9,
      "prayers":{
        "fajr":"4:01",
        "sunrise":"5:19",
        "dhuhr":"11:29",
        "asr":"14:57",
        "maghrib":"17:42",
        "isha":"19:12"
      }
    },
    {
      "date":"15/9",
      "day":15,
      "month":9,
      "prayers":{
        "fajr":"4:02",
        "sunrise":"5:20",
        "dhuhr":"11:29",
        "asr":"14:57",
        "maghrib":"17:41",
        "isha":"19:11"
      }
    },
    {
      "date":"16/9",
      "day":16,
      "month":9,
      "prayers":{
        "fajr":"4:02",
        "sunrise":"5:20",
        "dhuhr":"11:29",
        "asr":"14:56",
        "maghrib":"17:40",
        "isha":"19:10"
      }
    },
    {
      "date":"17/9",
      "day":17,
      "month":9,
      "prayers":{
        "fajr":"4:03",
        "sunrise":"5:20",
        "dhuhr":"11:28",
        "asr":"14:56",
        "maghrib":"17:38",
        "isha":"19:08"
      }
    },
    {
      "date":"18/9",
      "day":18,
      "month":9,
      "prayers":{
        "fajr":"4:03",
        "sunrise":"5:21",
        "dhuhr":"11:28",
        "asr":"14:55",
        "maghrib":"17:37",
        "isha":"19:07"
      }
    },
    {
      "date":"19/9",
      "day":19,
      "month":9,
      "prayers":{
        "fajr":"4:04",
        "sunrise":"5:21",
        "dhuhr":"11:28",
        "asr":"14:55",
        "maghrib":"17:36",
        "isha":"19:06"
      }
    },
    {
      "date":"20/9",
      "day":20,
      "month":9,
      "prayers":{
        "fajr":"4:04",
        "sunrise":"5:22",
        "dhuhr":"11:27",
        "asr":"14:54",
        "maghrib":"17:35",
        "isha":"19:05"
      }
    },
    {
      "date":"21/9",
      "day":21,
      "month":9,
      "prayers":{
        "fajr":"4:05",
        "sunrise":"5:22",
        "dhuhr":"11:27",
        "asr":"14:54",
        "maghrib":"17:34",
        "isha":"19:04"
      }
    },
    {
      "date":"22/9",
      "day":22,
      "month":9,
      "prayers":{
        "fajr":"4:05",
        "sunrise":"5:22",
        "dhuhr":"11:27",
        "asr":"14:53",
        "maghrib":"17:33",
        "isha":"19:03"
      }
    },
    {
      "date":"23/9",
      "day":23,
      "month":9,
      "prayers":{
        "fajr":"4:05",
        "sunrise":"5:23",
        "dhuhr":"11:26",
        "asr":"14:52",
        "maghrib":"17:32",
        "isha":"19:02"
      }
    },
    {
      "date":"24/9",
      "day":24,
      "month":9,
      "prayers":{
        "fajr":"4:06",
        "sunrise":"5:23",
        "dhuhr":"11:26",
        "asr":"14:52",
        "maghrib":"17:31",
        "isha":"19:01"
      }
    },
    {
      "date":"25/9",
      "day":25,
      "month":9,
      "prayers":{
        "fajr":"4:06",
        "sunrise":"5:23",
        "dhuhr":"11:26",
        "asr":"14:51",
        "maghrib":"17:30",
        "isha":"19:00"
      }
    },
    {
      "date":"26/9",
      "day":26,
      "month":9,
      "prayers":{
        "fajr":"4:07",
        "sunrise":"5:24",
        "dhuhr":"11:25",
        "asr":"14:51",
        "maghrib":"17:29",
        "isha":"18:59"
      }
    },
    {
      "date":"27/9",
      "day":27,
      "month":9,
      "prayers":{
        "fajr":"4:07",
        "sunrise":"5:24",
        "dhuhr":"11:25",
        "asr":"14:50",
        "maghrib":"17:28",
        "isha":"18:58"
      }
    },
    {
      "date":"28/9",
      "day":28,
      "month":9,
      "prayers":{
        "fajr":"4:08",
        "sunrise":"5:25",
        "dhuhr":"11:25",
        "asr":"14:49",
        "maghrib":"17:26",
        "isha":"18:56"
      }
    },
    {
      "date":"29/9",
      "day":29,
      "month":9,
      "prayers":{
        "fajr":"4:08",
        "sunrise":"5:25",
        "dhuhr":"11:24",
        "asr":"14:49",
        "maghrib":"17:25",
        "isha":"18:55"
      }
    },
    {
      "date":"30/9",
      "day":30,
      "month":9,
      "prayers":{
        "fajr":"4:08",
        "sunrise":"5:25",
        "dhuhr":"11:24",
        "asr":"14:48",
        "maghrib":"17:24",
        "isha":"18:54"
      }
    },
    {
      "date":"1/10",
      "day":1,
      "month":10,
      "prayers":{
        "fajr":"4:09",
        "sunrise":"5:26",
        "dhuhr":"11:24",
        "asr":"14:48",
        "maghrib":"17:23",
        "isha":"18:53"
      }
    },
    {
      "date":"2/10",
      "day":2,
      "month":10,
      "prayers":{
        "fajr":"4:09",
        "sunrise":"5:26",
        "dhuhr":"11:23",
        "asr":"14:47",
        "maghrib":"17:22",
        "isha":"18:52"
      }
    },
    {
      "date":"3/10",
      "day":3,
      "month":10,
      "prayers":{
        "fajr":"4:10",
        "sunrise":"5:27",
        "dhuhr":"11:23",
        "asr":"14:46",
        "maghrib":"17:21",
        "isha":"18:51"
      }
    },
    {
      "date":"4/10",
      "day":4,
      "month":10,
      "prayers":{
        "fajr":"4:10",
        "sunrise":"5:27",
        "dhuhr":"11:23",
        "asr":"14:46",
        "maghrib":"17:20",
        "isha":"18:50"
      }
    },
    {
      "date":"5/10",
      "day":5,
      "month":10,
      "prayers":{
        "fajr":"4:10",
        "sunrise":"5:28",
        "dhuhr":"11:22",
        "asr":"14:45",
        "maghrib":"17:19",
        "isha":"18:49"
      }
    },
    {
      "date":"6/10",
      "day":6,
      "month":10,
      "prayers":{
        "fajr":"4:11",
        "sunrise":"5:28",
        "dhuhr":"11:22",
        "asr":"14:44",
        "maghrib":"17:18",
        "isha":"18:48"
      }
    },
    {
      "date":"7/10",
      "day":7,
      "month":10,
      "prayers":{
        "fajr":"4:11",
        "sunrise":"5:28",
        "dhuhr":"11:22",
        "asr":"14:44",
        "maghrib":"17:17",
        "isha":"18:47"
      }
    },
    {
      "date":"8/10",
      "day":8,
      "month":10,
      "prayers":{
        "fajr":"4:12",
        "sunrise":"5:29",
        "dhuhr":"11:21",
        "asr":"14:43",
        "maghrib":"17:16",
        "isha":"18:46"
      }
    },
    {
      "date":"9/10",
      "day":9,
      "month":10,
      "prayers":{
        "fajr":"4:12",
        "sunrise":"5:29",
        "dhuhr":"11:21",
        "asr":"14:42",
        "maghrib":"17:15",
        "isha":"18:45"
      }
    },
    {
      "date":"10/10",
      "day":10,
      "month":10,
      "prayers":{
        "fajr":"4:13",
        "sunrise":"5:30",
        "dhuhr":"11:21",
        "asr":"14:42",
        "maghrib":"17:14",
        "isha":"18:44"
      }
    },
    {
      "date":"11/10",
      "day":11,
      "month":10,
      "prayers":{
        "fajr":"4:13",
        "sunrise":"5:30",
        "dhuhr":"11:21",
        "asr":"14:41",
        "maghrib":"17:13",
        "isha":"18:43"
      }
    },
    {
      "date":"12/10",
      "day":12,
      "month":10,
      "prayers":{
        "fajr":"4:13",
        "sunrise":"5:31",
        "dhuhr":"11:20",
        "asr":"14:41",
        "maghrib":"17:12",
        "isha":"18:42"
      }
    },
    {
      "date":"13/10",
      "day":13,
      "month":10,
      "prayers":{
        "fajr":"4:14",
        "sunrise":"5:31",
        "dhuhr":"11:20",
        "asr":"14:40",
        "maghrib":"17:11",
        "isha":"18:41"
      }
    },
    {
      "date":"14/10",
      "day":14,
      "month":10,
      "prayers":{
        "fajr":"4:14",
        "sunrise":"5:32",
        "dhuhr":"11:20",
        "asr":"14:39",
        "maghrib":"17:10",
        "isha":"18:40"
      }
    },
    {
      "date":"15/10",
      "day":15,
      "month":10,
      "prayers":{
        "fajr":"4:15",
        "sunrise":"5:32",
        "dhuhr":"11:20",
        "asr":"14:39",
        "maghrib":"17:09",
        "isha":"18:39"
      }
    },
    {
      "date":"16/10",
      "day":16,
      "month":10,
      "prayers":{
        "fajr":"4:15",
        "sunrise":"5:33",
        "dhuhr":"11:19",
        "asr":"14:38",
        "maghrib":"17:08",
        "isha":"18:38"
      }
    },
    {
      "date":"17/10",
      "day":17,
      "month":10,
      "prayers":{
        "fajr":"4:16",
        "sunrise":"5:33",
        "dhuhr":"11:19",
        "asr":"14:38",
        "maghrib":"17:07",
        "isha":"18:37"
      }
    },
    {
      "date":"18/10",
      "day":18,
      "month":10,
      "prayers":{
        "fajr":"4:16",
        "sunrise":"5:34",
        "dhuhr":"11:19",
        "asr":"14:37",
        "maghrib":"17:06",
        "isha":"18:36"
      }
    },
    {
      "date":"19/10",
      "day":19,
      "month":10,
      "prayers":{
        "fajr":"4:17",
        "sunrise":"5:34",
        "dhuhr":"11:19",
        "asr":"14:36",
        "maghrib":"17:05",
        "isha":"18:35"
      }
    },
    {
      "date":"20/10",
      "day":20,
      "month":10,
      "prayers":{
        "fajr":"4:17",
        "sunrise":"5:35",
        "dhuhr":"11:19",
        "asr":"14:36",
        "maghrib":"17:04",
        "isha":"18:34"
      }
    },
    {
      "date":"21/10",
      "day":21,
      "month":10,
      "prayers":{
        "fajr":"4:17",
        "sunrise":"5:35",
        "dhuhr":"11:19",
        "asr":"14:35",
        "maghrib":"17:04",
        "isha":"18:34"
      }
    },
    {
      "date":"22/10",
      "day":22,
      "month":10,
      "prayers":{
        "fajr":"4:18",
        "sunrise":"5:36",
        "dhuhr":"11:18",
        "asr":"14:35",
        "maghrib":"17:03",
        "isha":"18:33"
      }
    },
    {
      "date":"23/10",
      "day":23,
      "month":10,
      "prayers":{
        "fajr":"4:18",
        "sunrise":"5:36",
        "dhuhr":"11:18",
        "asr":"14:34",
        "maghrib":"17:02",
        "isha":"18:32"
      }
    },
    {
      "date":"24/10",
      "day":24,
      "month":10,
      "prayers":{
        "fajr":"4:19",
        "sunrise":"5:37",
        "dhuhr":"11:18",
        "asr":"14:33",
        "maghrib":"17:01",
        "isha":"18:31"
      }
    },
    {
      "date":"25/10",
      "day":25,
      "month":10,
      "prayers":{
        "fajr":"4:19",
        "sunrise":"5:37",
        "dhuhr":"11:18",
        "asr":"14:33",
        "maghrib":"17:00",
        "isha":"18:30"
      }
    },
    {
      "date":"26/10",
      "day":26,
      "month":10,
      "prayers":{
        "fajr":"4:20",
        "sunrise":"5:38",
        "dhuhr":"11:18",
        "asr":"14:32",
        "maghrib":"17:00",
        "isha":"18:30"
      }
    },
    {
      "date":"27/10",
      "day":27,
      "month":10,
      "prayers":{
        "fajr":"4:20",
        "sunrise":"5:38",
        "dhuhr":"11:18",
        "asr":"14:32",
        "maghrib":"16:59",
        "isha":"18:29"
      }
    },
    {
      "date":"28/10",
      "day":28,
      "month":10,
      "prayers":{
        "fajr":"4:21",
        "sunrise":"5:39",
        "dhuhr":"11:18",
        "asr":"14:31",
        "maghrib":"16:58",
        "isha":"18:28"
      }
    },
    {
      "date":"29/10",
      "day":29,
      "month":10,
      "prayers":{
        "fajr":"4:21",
        "sunrise":"5:40",
        "dhuhr":"11:18",
        "asr":"14:31",
        "maghrib":"16:57",
        "isha":"18:27"
      }
    },
    {
      "date":"30/10",
      "day":30,
      "month":10,
      "prayers":{
        "fajr":"4:22",
        "sunrise":"5:40",
        "dhuhr":"11:18",
        "asr":"14:30",
        "maghrib":"16:57",
        "isha":"18:27"
      }
    },
    {
      "date":"31/10",
      "day":31,
      "month":10,
      "prayers":{
        "fajr":"4:22",
        "sunrise":"5:41",
        "dhuhr":"11:17",
        "asr":"14:30",
        "maghrib":"16:56",
        "isha":"18:26"
      }
    },
    {
      "date":"1/11",
      "day":1,
      "month":11,
      "prayers":{
        "fajr":"4:23",
        "sunrise":"5:41",
        "dhuhr":"11:17",
        "asr":"14:29",
        "maghrib":"16:55",
        "isha":"18:25"
      }
    },
    {
      "date":"2/11",
      "day":2,
      "month":11,
      "prayers":{
        "fajr":"4:23",
        "sunrise":"5:42",
        "dhuhr":"11:17",
        "asr":"14:29",
        "maghrib":"16:55",
        "isha":"18:25"
      }
    },
    {
      "date":"3/11",
      "day":3,
      "month":11,
      "prayers":{
        "fajr":"4:24",
        "sunrise":"5:43",
        "dhuhr":"11:17",
        "asr":"14:28",
        "maghrib":"16:54",
        "isha":"18:24"
      }
    },
    {
      "date":"4/11",
      "day":4,
      "month":11,
      "prayers":{
        "fajr":"4:24",
        "sunrise":"5:43",
        "dhuhr":"11:17",
        "asr":"14:28",
        "maghrib":"16:53",
        "isha":"18:23"
      }
    },
    {
      "date":"5/11",
      "day":5,
      "month":11,
      "prayers":{
        "fajr":"4:25",
        "sunrise":"5:44",
        "dhuhr":"11:17",
        "asr":"14:28",
        "maghrib":"16:53",
        "isha":"18:23"
      }
    },
    {
      "date":"6/11",
      "day":6,
      "month":11,
      "prayers":{
        "fajr":"4:25",
        "sunrise":"5:45",
        "dhuhr":"11:17",
        "asr":"14:27",
        "maghrib":"16:52",
        "isha":"18:22"
      }
    },
    {
      "date":"7/11",
      "day":7,
      "month":11,
      "prayers":{
        "fajr":"4:26",
        "sunrise":"5:45",
        "dhuhr":"11:18",
        "asr":"14:27",
        "maghrib":"16:52",
        "isha":"18:22"
      }
    },
    {
      "date":"8/11",
      "day":8,
      "month":11,
      "prayers":{
        "fajr":"4:26",
        "sunrise":"5:46",
        "dhuhr":"11:18",
        "asr":"14:26",
        "maghrib":"16:51",
        "isha":"18:21"
      }
    },
    {
      "date":"9/11",
      "day":9,
      "month":11,
      "prayers":{
        "fajr":"4:27",
        "sunrise":"5:47",
        "dhuhr":"11:18",
        "asr":"14:26",
        "maghrib":"16:50",
        "isha":"18:20"
      }
    },
    {
      "date":"10/11",
      "day":10,
      "month":11,
      "prayers":{
        "fajr":"4:28",
        "sunrise":"5:47",
        "dhuhr":"11:18",
        "asr":"14:26",
        "maghrib":"16:50",
        "isha":"18:20"
      }
    },
    {
      "date":"11/11",
      "day":11,
      "month":11,
      "prayers":{
        "fajr":"4:28",
        "sunrise":"5:48",
        "dhuhr":"11:18",
        "asr":"14:25",
        "maghrib":"16:50",
        "isha":"18:20"
      }
    },
    {
      "date":"12/11",
      "day":12,
      "month":11,
      "prayers":{
        "fajr":"4:29",
        "sunrise":"5:49",
        "dhuhr":"11:18",
        "asr":"14:25",
        "maghrib":"16:49",
        "isha":"18:19"
      }
    },
    {
      "date":"13/11",
      "day":13,
      "month":11,
      "prayers":{
        "fajr":"4:29",
        "sunrise":"5:49",
        "dhuhr":"11:18",
        "asr":"14:25",
        "maghrib":"16:49",
        "isha":"18:19"
      }
    },
    {
      "date":"14/11",
      "day":14,
      "month":11,
      "prayers":{
        "fajr":"4:30",
        "sunrise":"5:50",
        "dhuhr":"11:18",
        "asr":"14:25",
        "maghrib":"16:48",
        "isha":"18:18"
      }
    },
    {
      "date":"15/11",
      "day":15,
      "month":11,
      "prayers":{
        "fajr":"4:30",
        "sunrise":"5:51",
        "dhuhr":"11:18",
        "asr":"14:24",
        "maghrib":"16:48",
        "isha":"18:18"
      }
    },
    {
      "date":"16/11",
      "day":16,
      "month":11,
      "prayers":{
        "fajr":"4:31",
        "sunrise":"5:51",
        "dhuhr":"11:19",
        "asr":"14:24",
        "maghrib":"16:48",
        "isha":"18:18"
      }
    },
    {
      "date":"17/11",
      "day":17,
      "month":11,
      "prayers":{
        "fajr":"4:32",
        "sunrise":"5:52",
        "dhuhr":"11:19",
        "asr":"14:24",
        "maghrib":"16:47",
        "isha":"18:17"
      }
    },
    {
      "date":"18/11",
      "day":18,
      "month":11,
      "prayers":{
        "fajr":"4:32",
        "sunrise":"5:53",
        "dhuhr":"11:19",
        "asr":"14:24",
        "maghrib":"16:47",
        "isha":"18:17"
      }
    },
    {
      "date":"19/11",
      "day":19,
      "month":11,
      "prayers":{
        "fajr":"4:33",
        "sunrise":"5:53",
        "dhuhr":"11:19",
        "asr":"14:24",
        "maghrib":"16:47",
        "isha":"18:17"
      }
    },
    {
      "date":"20/11",
      "day":20,
      "month":11,
      "prayers":{
        "fajr":"4:33",
        "sunrise":"5:54",
        "dhuhr":"11:19",
        "asr":"14:23",
        "maghrib":"16:46",
        "isha":"18:16"
      }
    },
    {
      "date":"21/11",
      "day":21,
      "month":11,
      "prayers":{
        "fajr":"4:34",
        "sunrise":"5:55",
        "dhuhr":"11:20",
        "asr":"14:23",
        "maghrib":"16:46",
        "isha":"18:16"
      }
    },
    {
      "date":"22/11",
      "day":22,
      "month":11,
      "prayers":{
        "fajr":"4:35",
        "sunrise":"5:56",
        "dhuhr":"11:20",
        "asr":"14:23",
        "maghrib":"16:46",
        "isha":"18:16"
      }
    },
    {
      "date":"23/11",
      "day":23,
      "month":11,
      "prayers":{
        "fajr":"4:35",
        "sunrise":"5:56",
        "dhuhr":"11:20",
        "asr":"14:23",
        "maghrib":"16:46",
        "isha":"18:16"
      }
    },
    {
      "date":"24/11",
      "day":24,
      "month":11,
      "prayers":{
        "fajr":"4:36",
        "sunrise":"5:57",
        "dhuhr":"11:20",
        "asr":"14:23",
        "maghrib":"16:46",
        "isha":"18:16"
      }
    },
    {
      "date":"25/11",
      "day":25,
      "month":11,
      "prayers":{
        "fajr":"4:37",
        "sunrise":"5:58",
        "dhuhr":"11:21",
        "asr":"14:23",
        "maghrib":"16:45",
        "isha":"18:15"
      }
    },
    {
      "date":"26/11",
      "day":26,
      "month":11,
      "prayers":{
        "fajr":"4:37",
        "sunrise":"5:59",
        "dhuhr":"11:21",
        "asr":"14:23",
        "maghrib":"16:45",
        "isha":"18:15"
      }
    },
    {
      "date":"27/11",
      "day":27,
      "month":11,
      "prayers":{
        "fajr":"4:38",
        "sunrise":"5:59",
        "dhuhr":"11:21",
        "asr":"14:23",
        "maghrib":"16:45",
        "isha":"18:15"
      }
    },
    {
      "date":"28/11",
      "day":28,
      "month":11,
      "prayers":{
        "fajr":"4:38",
        "sunrise":"6:00",
        "dhuhr":"11:22",
        "asr":"14:23",
        "maghrib":"16:45",
        "isha":"18:15"
      }
    },
    {
      "date":"29/11",
      "day":29,
      "month":11,
      "prayers":{
        "fajr":"4:39",
        "sunrise":"6:01",
        "dhuhr":"11:22",
        "asr":"14:23",
        "maghrib":"16:45",
        "isha":"18:15"
      }
    },
    {
      "date":"30/11",
      "day":30,
      "month":11,
      "prayers":{
        "fajr":"4:40",
        "sunrise":"6:01",
        "dhuhr":"11:22",
        "asr":"14:23",
        "maghrib":"16:45",
        "isha":"18:15"
      }
    },
    {
      "date":"1/12",
      "day":1,
      "month":12,
      "prayers":{
        "fajr":"4:40",
        "sunrise":"6:02",
        "dhuhr":"11:23",
        "asr":"14:23",
        "maghrib":"16:45",
        "isha":"18:15"
      }
    },
    {
      "date":"2/12",
      "day":2,
      "month":12,
      "prayers":{
        "fajr":"4:41",
        "sunrise":"6:03",
        "dhuhr":"11:23",
        "asr":"14:23",
        "maghrib":"16:45",
        "isha":"18:15"
      }
    },
    {
      "date":"3/12",
      "day":3,
      "month":12,
      "prayers":{
        "fajr":"4:42",
        "sunrise":"6:04",
        "dhuhr":"11:24",
        "asr":"14:23",
        "maghrib":"16:45",
        "isha":"18:15"
      }
    },
    {
      "date":"4/12",
      "day":4,
      "month":12,
      "prayers":{
        "fajr":"4:42",
        "sunrise":"6:04",
        "dhuhr":"11:24",
        "asr":"14:24",
        "maghrib":"16:45",
        "isha":"18:15"
      }
    },
    {
      "date":"5/12",
      "day":5,
      "month":12,
      "prayers":{
        "fajr":"4:43",
        "sunrise":"6:05",
        "dhuhr":"11:24",
        "asr":"14:24",
        "maghrib":"16:46",
        "isha":"18:16"
      }
    },
    {
      "date":"6/12",
      "day":6,
      "month":12,
      "prayers":{
        "fajr":"4:43",
        "sunrise":"6:06",
 Exported 365 days to JSON
       "dhuhr":"11:25",
        "asr":"14:24",
        "maghrib":"16:46",
        "isha":"18:16"
      }
    },
    {
      "date":"7/12",
      "day":7,
      "month":12,
      "prayers":{
        "fajr":"4:44",
        "sunrise":"6:06",
        "dhuhr":"11:25",
        "asr":"14:24",
        "maghrib":"16:46",
        "isha":"18:16"
      }
    },
    {
      "date":"8/12",
      "day":8,
      "month":12,
      "prayers":{
        "fajr":"4:45",
        "sunrise":"6:07",
        "dhuhr":"11:26",
        "asr":"14:24",
        "maghrib":"16:46",
        "isha":"18:16"
      }
    },
    {
      "date":"9/12",
      "day":9,
      "month":12,
      "prayers":{
        "fajr":"4:45",
        "sunrise":"6:08",
        "dhuhr":"11:26",
        "asr":"14:25",
        "maghrib":"16:46",
        "isha":"18:16"
      }
    },
    {
      "date":"10/12",
      "day":10,
      "month":12,
      "prayers":{
        "fajr":"4:46",
        "sunrise":"6:08",
        "dhuhr":"11:27",
        "asr":"14:25",
        "maghrib":"16:47",
        "isha":"18:17"
      }
    },
    {
      "date":"11/12",
      "day":11,
      "month":12,
      "prayers":{
        "fajr":"4:46",
        "sunrise":"6:09",
        "dhuhr":"11:27",
        "asr":"14:25",
        "maghrib":"16:47",
        "isha":"18:17"
      }
    },
    {
      "date":"12/12",
      "day":12,
      "month":12,
      "prayers":{
        "fajr":"4:47",
        "sunrise":"6:10",
        "dhuhr":"11:27",
        "asr":"14:25",
        "maghrib":"16:47",
        "isha":"18:17"
      }
    },
    {
      "date":"13/12",
      "day":13,
      "month":12,
      "prayers":{
        "fajr":"4:48",
        "sunrise":"6:10",
        "dhuhr":"11:28",
        "asr":"14:26",
        "maghrib":"16:47",
        "isha":"18:17"
      }
    },
    {
      "date":"14/12",
      "day":14,
      "month":12,
      "prayers":{
        "fajr":"4:48",
        "sunrise":"6:11",
        "dhuhr":"11:28",
        "asr":"14:26",
        "maghrib":"16:48",
        "isha":"18:18"
      }
    },
    {
      "date":"15/12",
      "day":15,
      "month":12,
      "prayers":{
        "fajr":"4:49",
        "sunrise":"6:11",
        "dhuhr":"11:29",
        "asr":"14:27",
        "maghrib":"16:48",
        "isha":"18:18"
      }
    },
    {
      "date":"16/12",
      "day":16,
      "month":12,
      "prayers":{
        "fajr":"4:49",
        "sunrise":"6:12",
        "dhuhr":"11:29",
        "asr":"14:27",
        "maghrib":"16:49",
        "isha":"18:19"
      }
    },
    {
      "date":"17/12",
      "day":17,
      "month":12,
      "prayers":{
        "fajr":"4:50",
        "sunrise":"6:13",
        "dhuhr":"11:30",
        "asr":"14:27",
        "maghrib":"16:49",
        "isha":"18:19"
      }
    },
    {
      "date":"18/12",
      "day":18,
      "month":12,
      "prayers":{
        "fajr":"4:50",
        "sunrise":"6:13",
        "dhuhr":"11:30",
        "asr":"14:28",
        "maghrib":"16:49",
        "isha":"18:19"
      }
    },
    {
      "date":"19/12",
      "day":19,
      "month":12,
      "prayers":{
        "fajr":"4:51",
        "sunrise":"6:14",
        "dhuhr":"11:31",
        "asr":"14:28",
        "maghrib":"16:50",
        "isha":"18:20"
      }
    },
    {
      "date":"20/12",
      "day":20,
      "month":12,
      "prayers":{
        "fajr":"4:52",
        "sunrise":"6:14",
        "dhuhr":"11:31",
        "asr":"14:29",
        "maghrib":"16:50",
        "isha":"18:20"
      }
    },
    {
      "date":"21/12",
      "day":21,
      "month":12,
      "prayers":{
        "fajr":"4:52",
        "sunrise":"6:15",
        "dhuhr":"11:32",
        "asr":"14:29",
        "maghrib":"16:51",
        "isha":"18:21"
      }
    },
    {
      "date":"22/12",
      "day":22,
      "month":12,
      "prayers":{
        "fajr":"4:53",
        "sunrise":"6:15",
        "dhuhr":"11:32",
        "asr":"14:30",
        "maghrib":"16:51",
        "isha":"18:21"
      }
    },
    {
      "date":"23/12",
      "day":23,
      "month":12,
      "prayers":{
        "fajr":"4:53",
        "sunrise":"6:16",
        "dhuhr":"11:33",
        "asr":"14:30",
        "maghrib":"16:52",
        "isha":"18:22"
      }
    },
    {
      "date":"24/12",
      "day":24,
      "month":12,
      "prayers":{
        "fajr":"4:53",
        "sunrise":"6:16",
        "dhuhr":"11:33",
        "asr":"14:31",
        "maghrib":"16:52",
        "isha":"18:22"
      }
    },
    {
      "date":"25/12",
      "day":25,
      "month":12,
      "prayers":{
        "fajr":"4:54",
        "sunrise":"6:17",
        "dhuhr":"11:34",
        "asr":"14:31",
        "maghrib":"16:53",
        "isha":"18:23"
      }
    },
    {
      "date":"26/12",
      "day":26,
      "month":12,
      "prayers":{
        "fajr":"4:54",
        "sunrise":"6:17",
        "dhuhr":"11:34",
        "asr":"14:32",
        "maghrib":"16:53",
        "isha":"18:23"
      }
    },
    {
      "date":"27/12",
      "day":27,
      "month":12,
      "prayers":{
        "fajr":"4:55",
        "sunrise":"6:18",
        "dhuhr":"11:35",
        "asr":"14:32",
        "maghrib":"16:54",
        "isha":"18:24"
      }
    },
    {
      "date":"28/12",
      "day":28,
      "month":12,
      "prayers":{
        "fajr":"4:55",
        "sunrise":"6:18",
        "dhuhr":"11:35",
        "asr":"14:33",
        "maghrib":"16:55",
        "isha":"18:25"
      }
    },
    {
      "date":"29/12",
      "day":29,
      "month":12,
      "prayers":{
        "fajr":"4:56",
        "sunrise":"6:18",
        "dhuhr":"11:36",
        "asr":"14:34",
        "maghrib":"16:55",
        "isha":"18:25"
      }
    },
    {
      "date":"30/12",
      "day":30,
      "month":12,
      "prayers":{
        "fajr":"4:56",
        "sunrise":"6:19",
        "dhuhr":"11:36",
        "asr":"14:34",
        "maghrib":"16:56",
        "isha":"18:26"
      }
    },
    {
      "date":"31/12",
      "day":31,
      "month":12,
      "prayers":{
        "fajr":"4:56",
        "sunrise":"6:19",
        "dhuhr":"11:37",
        "asr":"14:35",
        "maghrib":"16:56",
        "isha":"18:26"
      }
    }
  ]
}
